tools_create_tables/__init__.py
tools_create_tables/modulo.py
create_tables_storage-0.1.15.dist-info/METADATA
create_tables_storage-0.1.15.dist-info/WHEEL
create_tables_storage-0.1.15.dist-info/RECORD
