Metadata-Version: 2.3
Name: create_tables_storage
Version: 0.1.15
Summary: Libreria de creacion de tablas para un proyecto de migracion
License: MIT
Author: Pablo Ramirez A
Author-email: pramireza@payutic.pro
Requires-Python: >=3.11.7,<4.0.0
Classifier: License :: OSI Approved :: MIT License
Classifier: Programming Language :: Python :: 3
Classifier: Programming Language :: Python :: 3.12
Classifier: Programming Language :: Python :: 3.13
